src/worker_pool.py
src/worker_pool_test.py
twerkpool-0.0.1.dist-info/METADATA
twerkpool-0.0.1.dist-info/WHEEL
twerkpool-0.0.1.dist-info/RECORD
